{"title": "Dolphins and Humans Have Similar Personality Traits", "description": "A study of dolphins reveals some amazing facts", "wordCount": 267, "difficulty": "Difficult", "grade": 10.98, "rating": 8.44, "content": [[[""]], [["A study has "], ["found", "ielts-high ielts"], [" that Dolphins have developed several of the same "], ["features", "ielts-high ielts", "feature"], [" as humans, even though "], ["dolphins", "cet6 cet6-low", "dolphin"], [" and humans "], ["evolved", "ielts-low cet6-low cet6 ielts", "evolve"], [" in vastly different "], ["surroundings", "cet6 cet6-low"], [".\n"]], [["Researchers", "cet6-med cet6", "researcher"], [" did a study of 134 male and "], ["female", "ielts-high ielts"], [" bottlenose "], ["dolphins", "cet6 cet6-low", "dolphin"], [" at 8 "], ["facilities", "ielts-med ielts", "facility"], [" in different countries. The "], ["dolphins", "cet6 cet6-low", "dolphin"], [" were not studied as a group but as "], ["individuals", "ielts-high ielts", "individual"], [". The study showed that humans and bottlenose "], ["dolphins", "cet6 cet6-low", "dolphin"], [" have certain "], ["personality", "ielts-high cet6-med cet6 ielts"], [" "], ["traits", "cet6 cet6-low", "trait"], [" which are "], ["similar", "ielts-high ielts"], [". They "], ["found", "ielts-high ielts"], [" two "], ["traits", "cet6 cet6-low", "trait"], [" that are the same - being "], ["curious", "ielts-med cet6-med cet6 ielts"], [" and being social.\n"]], [["This has helped "], ["researchers", "cet6-med cet6", "researcher"], [" understand how some human "], ["personality", "ielts-high cet6-med cet6 ielts"], [" "], ["traits", "cet6 cet6-low", "trait"], [" developed without being "], ["influenced", "cet6-high ielts-high cet6 ielts", "influence"], [" by the "], ["environment", "ielts-high ielts"], [" they are in. This was also "], ["found", "ielts-high ielts"], [" when studying "], ["dolphins", "cet6 cet6-low", "dolphin"], [", "], ["despite", "cet6-high ielts-high cet6 ielts"], [" having "], ["evolved", "ielts-low cet6-low cet6 ielts", "evolve"], [" in a vastly different "], ["environment", "ielts-high ielts"], [".\n"]], [["Dr Morton, who led this "], ["research", "ielts-high ielts"], [", said that it was the first time that the "], ["personality", "ielts-high cet6-med cet6 ielts"], [" of "], ["dolphins", "cet6 cet6-low", "dolphin"], [" had been studied in this way. He also said they thought "], ["dolphins", "cet6 cet6-low", "dolphin"], [" were a great animal for this kind of study because they are "], ["intelligent", "cet6-high ielts-med cet6 ielts"], [" and social just like humans. These are two "], ["traits", "cet6 cet6-low", "trait"], [" that "], ["contribute", "cet6-high ielts-high cet6 ielts"], [" to "], ["personality", "ielts-high cet6-med cet6 ielts"], [".\n"]], [["Dolphins", "cet6 cet6-low", "dolphin"], [", like many primates, have larger "], ["brains", "cet6-high ielts-high cet6 ielts", "brain"], [" than what the body needs to "], ["function", "ielts-high ielts"], [". The part that is not used to make the body "], ["function", "ielts-high ielts"], [" is used for "], ["intelligence", "cet6-high ielts-high cet6 ielts"], [". "], ["Intelligence", "cet6-high ielts-high cet6 ielts", "intelligence"], [" gives primates the "], ["ability", "ielts-high ielts"], [" to be "], ["curious", "ielts-med cet6-med cet6 ielts"], [".\n"]], [["Dr Morton wants us to understand that some "], ["personality", "ielts-high cet6-med cet6 ielts"], [" "], ["traits", "cet6 cet6-low", "trait"], [" in "], ["dolphins", "cet6 cet6-low", "dolphin"], [" and humans are the same, but this does not mean that that all "], ["personality", "ielts-high cet6-med cet6 ielts"], [" "], ["traits", "cet6 cet6-low", "trait"], [" are the same.\n"]], [["This study began in 2012 and was "], ["conducted", "cet6-high ielts-high cet6 ielts", "conduct"], [" at "], ["facilities", "ielts-med ielts", "facility"], [" in Mexico, America, France, the Bahamas, and the Cayman Islands."]]]}