{"title": "Man Claims Wife Is Dead - But She Is Not", "description": "A woman dating a man who said his wife had died, discovered to her horror that his wife was still very much alive and still in a relationship with him", "wordCount": 255, "difficulty": "Medium", "grade": 7.39, "rating": 5.68, "content": [[[""]], [["The man said he had a son, and that "], ["sadly", "cet6-low cet6"], [" his son\u2019s mother had died in a "], ["tragic", "cet6-low cet6"], [" "], ["accident", "cet6-high ielts-high ielts cet6"], [".  His girlfriend wanted to know how his wife had died and "], ["decided", "cet6-high cet6"], [" to find out by going onto his wife's online social "], ["media", "ielts-high ielts", "medium"], [".\n"]], [["She then "], ["discovered", "cet6-high cet6", "discover"], [" that his supposedly dead wife was still uploading photos and that she was not dead but rather was still in a relationship with her "], ["husband", "cet6-high ielts-high ielts cet6"], [".  His girlfriend then did more searching online and "], ["discovered", "cet6-high cet6", "discover"], [" that his wife had "], ["posted", "ielts-high ielts", "post"], [" even more photos.  She "], ["found", "ielts-high ielts"], [" his wife's whole family and "], ["career", "ielts-high ielts"], [" history on the internet.  She was very much "], ["alive", "cet6-high cet6"], ["!\n"]], [["She "], ["confronted", "ielts-low cet6-low ielts cet6", "confront"], [" him. He "], ["denied", "cet6-med ielts-med ielts cet6", "deny"], [" the fact that his wife was still "], ["alive", "cet6-high cet6"], [" and said his girlfriend was "], ["lying", "cet6-high cet6", "lie"], [".  When her friends asked her whether she had "], ["contacted", "ielts-high ielts", "contact"], [" his wife she said she had but that the wife had never read her messages.\n"]], [["His girlfriend shared her story online: she went on a "], ["date", "ielts-high ielts"], [" with him and "], ["found", "ielts-high ielts"], [" out that he "], ["taught", "cet6-high cet6", "teach"], [" school children.  She thought it was very \""], ["sweet", "cet6-high cet6"], ["\".  He said he was 25 years old and a "], ["single", "ielts-high ielts"], [" father to his son.  He told her that when he went on "], ["dates", "ielts-high ielts", "date"], [", the other teachers looked after his son.  He liked running and "], ["seemed", "cet6-high cet6", "seem"], [" a very normal person.\n"]], [["Many viewers who read her story said they had had "], ["similar", "ielts-high ielts"], [" experiences."]]], "date": "20-june-2021"}