{"title": "An Aurora Might Be the Reason the Titanic Sank", "description": "A witness recalled that the northern lights were very strong on the night the Titanic sank", "wordCount": 334, "difficulty": "Medium", "grade": 8.71, "rating": 6.7, "content": [[[""]], [["The "], ["date", "ielts-high ielts"], [" was April 15, 1912. This "], ["disaster", "cet6-high ielts-high ielts cet6"], [" "], ["killed", "cet6-high cet6", "kill"], [" more than 1 500 "], ["passengers", "cet6-high cet6", "passenger"], [".\n"]], [["Auroras shimmered in "], ["skies", "cet6-high cet6", "sky"], [" over the northern "], ["Atlantic", "cet6-high cet6", "atlantic"], [" that night. An "], ["observer", "cet6-med cet6"], [" "], ["testified", "ielts-low cet6-low ielts cet6", "testify"], [" that the northern "], ["lights", "ielts-high ielts", "light"], [" (the auroras) were very strong, and eyewitnesses "], ["described", "cet6-high cet6", "describe"], [" "], ["glows", "cet6-med ielts-low ielts cet6", "glow"], [" in the "], ["sky", "cet6-high cet6"], [" as the Titanic went down. New "], ["research", "ielts-high ielts"], [" "], ["hints", "cet6-med ielts-med ielts cet6", "hint"], [" that the "], ["storm", "cet6-high cet6"], [" behind the northern "], ["lights", "ielts-high ielts", "light"], [" could have "], ["disrupted", "cet6-low cet6", "disrupt"], [" the ship's "], ["navigation", "ielts-low ielts"], [" and "], ["communication", "ielts-high ielts"], [" "], ["systems", "ielts-high ielts", "system"], [". It might even have "], ["hampered", "ielts-low cet6-low ielts cet6", "hamper"], [" "], ["rescue", "cet6-high ielts-med ielts cet6"], [" "], ["efforts", "cet6-high ielts-high ielts cet6", "effort"], [".\n"]], [["When high-speed "], ["streams", "cet6-high cet6", "stream"], [" of electrified gas "], ["shoot", "cet6-high cet6"], [" down to Earth from the sun, it is called a "], ["solar", "cet6-high ielts-med ielts cet6"], [" "], ["storm", "cet6-high cet6"], [". Auroras form from "], ["solar", "cet6-high ielts-med ielts cet6"], [" "], ["storms", "cet6-high cet6", "storm"], [". These "], ["solar", "cet6-high ielts-med ielts cet6"], [" "], ["storms", "cet6-high cet6", "storm"], [" "], ["create", "ielts-high ielts"], [" a lot of "], ["energy", "ielts-high ielts"], [" when they "], ["collide", "ielts-low cet6-low ielts cet6"], [" with Earth\u2019s "], ["atmosphere", "cet6-high ielts-high ielts cet6"], [". This "], ["causes", "ielts-high ielts", "cause"], [" them to "], ["glow", "cet6-med ielts-low ielts cet6"], [" green, red, "], ["purple", "cet6-high ielts-med ielts cet6"], [", and blue.\n"]], [["If a "], ["solar", "cet6-high ielts-med ielts cet6"], [" "], ["storm", "cet6-high cet6"], [" was "], ["powerful", "cet6-high cet6"], [" enough to "], ["produce", "cet6-high ielts-high ielts cet6"], [" an aurora, it may have "], ["affected", "cet6-high ielts-high ielts cet6", "affect"], [" "], ["compasses", "ielts-low cet6-low ielts cet6", "compass"], [" and wireless "], ["communication", "ielts-high ielts"], [" on the Titanic. It would also have "], ["affected", "cet6-high ielts-high ielts cet6", "affect"], [" other ships in the "], ["area", "ielts-high ielts"], [" that tried to come to the "], ["rescue", "cet6-high ielts-med ielts cet6"], [" of the Titanic.\n"]], [["According", "cet6-med ielts-low ielts cet6", "accord"], [" to James Bisset, of the RMS Carpathia, there was no "], ["moon", "cet6-high cet6"], [", but the Aurora "], ["glittered", "ielts-low cet6-low ielts cet6", "glitter"], [" in the "], ["sky", "cet6-high cet6"], [". The Carpathia was used in the "], ["rescue", "cet6-high ielts-med ielts cet6"], [" of the "], ["survivors", "ielts-low ielts", "survivor"], [" of the Titanic.\n"]], [["The northern "], ["lights", "ielts-high ielts", "light"], [" were also seen by the "], ["survivors", "ielts-low ielts", "survivor"], [" from their lifeboats at around 3 a.m. Lawrence Beesley, a Titanic "], ["survivor", "ielts-low ielts"], [", wrote that the "], ["glow", "cet6-med ielts-low ielts cet6"], [" \"arched fanwise "], ["across", "ielts-high ielts"], [" the northern "], ["sky", "cet6-high cet6"], [", with "], ["faint", "cet6-low ielts-med ielts cet6"], [" streamers "], ["reaching", "cet6-high cet6", "reach"], [" towards the "], ["Pole", "cet6-med ielts-med ielts cet6", "pole"], ["-star.\"\n"]], [["While the "], ["solar", "cet6-high ielts-med ielts cet6"], [" "], ["storm", "cet6-high cet6"], [" was "], ["generating", "cet6-high ielts-med ielts cet6", "generate"], [" a beautiful "], ["light", "ielts-high ielts"], [" in the "], ["sky", "cet6-high cet6"], [", it could have also been "], ["disrupting", "cet6-low cet6", "disrupt"], [" the Titanic's "], ["compass", "ielts-low cet6-low ielts cet6"], [". A "], ["mere", "cet6-med ielts-high ielts cet6"], [" 0.5 degrees would have been enough for the Titanic to go off-course and place it on a course where it "], ["collided", "ielts-low cet6-low ielts cet6", "collide"], [" with the iceberg.\n"]], [["It is "], ["proposed", "cet6-med ielts-med ielts cet6", "propose"], [", that if the disruption from a "], ["solar", "cet6-high ielts-med ielts cet6"], [" "], ["storm", "cet6-high cet6"], [" did take place, it could have "], ["influenced", "cet6-high ielts-high ielts cet6", "influence"], [" "], ["distress", "cet6-low ielts-med ielts cet6"], [" "], ["signals", "cet6-high ielts-high ielts cet6", "signal"], [" that were sent out from the Titanic. This would have "], ["delayed", "cet6-high ielts-high ielts cet6", "delay"], [" the "], ["arrival", "cet6-high cet6"], [" of any "], ["rescue", "cet6-high ielts-med ielts cet6"], [" ships."]]], "date": "06-june-2021"}